LICENSE
README.md
setup.py
climetlab_maelstrom_yr/__init__.py
climetlab_maelstrom_yr/yr.py
climetlab_maelstrom_yr.egg-info/PKG-INFO
climetlab_maelstrom_yr.egg-info/SOURCES.txt
climetlab_maelstrom_yr.egg-info/dependency_links.txt
climetlab_maelstrom_yr.egg-info/entry_points.txt
climetlab_maelstrom_yr.egg-info/requires.txt
climetlab_maelstrom_yr.egg-info/top_level.txt
climetlab_maelstrom_yr.egg-info/zip-safe