Metadata-Version: 2.1
Name: climetlab-maelstrom-yr
Version: 0.6.2
Summary: A dataset plugin for climetlab for the dataset maelstrom-yr/yr.
Home-page: https://github.com/metno/climetlab-maelstrom-yr
Author: Thomas Nipen
Author-email: thomasn@met.no
License: Apache License Version 2.0
Keywords: meteorology
Platform: UNKNOWN
Classifier: Development Status :: 3 - Alpha
Classifier: Intended Audience :: Developers
Classifier: License :: OSI Approved :: Apache Software License
Classifier: Programming Language :: Python :: 3
Classifier: Programming Language :: Python :: 3.6
Classifier: Programming Language :: Python :: 3.7
Classifier: Programming Language :: Python :: 3.8
Classifier: Programming Language :: Python :: 3.9
Classifier: Programming Language :: Python :: Implementation :: CPython
Classifier: Programming Language :: Python :: Implementation :: PyPy
Classifier: Operating System :: OS Independent
Provides-Extra: test
